delta_lens/__init__.py
delta_lens/cli.py
delta_lens/config.py
delta_lens/config_schema.json
delta_lens/csvExport.py
delta_lens/deltaLens.py
delta_lens/sqliteExport.py
delta_lens-0.1.10.dist-info/METADATA
delta_lens-0.1.10.dist-info/WHEEL
delta_lens-0.1.10.dist-info/entry_points.txt
delta_lens-0.1.10.dist-info/top_level.txt
delta_lens-0.1.10.dist-info/RECORD
