Metadata-Version: 2.2
Name: delta-lens
Version: 0.1.10
Summary: A tool for comparing large datasets using DuckDB
Home-page: https://github.com/unclepaul84/duck-db-datacompare
Author: Paul
Author-email: unclepaul84@gmail.com
Classifier: Development Status :: 4 - Beta
Classifier: Intended Audience :: Developers
Classifier: License :: OSI Approved :: MIT License
Classifier: Operating System :: OS Independent
Classifier: Programming Language :: Python :: 3.9
Classifier: Programming Language :: Python :: 3.10
Classifier: Programming Language :: Python :: 3.11
Classifier: Programming Language :: Python :: 3.12
Classifier: Topic :: Software Development :: Libraries :: Python Modules
Classifier: Topic :: Database
Requires-Python: >=3.9
Requires-Dist: duckdb>=1.2.0
Requires-Dist: pandas>=2.2.3
Requires-Dist: numpy>=2.2.2
Requires-Dist: jsonschema>=4.23.0
Dynamic: author
Dynamic: author-email
Dynamic: classifier
Dynamic: description
Dynamic: description-content-type
Dynamic: home-page
Dynamic: requires-dist
Dynamic: requires-python
Dynamic: summary
